README.md
setup.py
src/gdmTool/__init__.py
src/gdmTool/pic2matrix.py
src/gdmTool.egg-info/PKG-INFO
src/gdmTool.egg-info/SOURCES.txt
src/gdmTool.egg-info/dependency_links.txt
src/gdmTool.egg-info/requires.txt
src/gdmTool.egg-info/top_level.txt